airflow/providers/ftp/LICENSE
airflow/providers/ftp/__init__.py
airflow/providers/ftp/get_provider_info.py
airflow/providers/ftp/hooks/__init__.py
airflow/providers/ftp/hooks/ftp.py
airflow/providers/ftp/operators/__init__.py
airflow/providers/ftp/operators/ftp.py
airflow/providers/ftp/sensors/__init__.py
airflow/providers/ftp/sensors/ftp.py
apache_airflow_providers_ftp-3.12.1.dist-info/entry_points.txt
apache_airflow_providers_ftp-3.12.1.dist-info/WHEEL
apache_airflow_providers_ftp-3.12.1.dist-info/METADATA
apache_airflow_providers_ftp-3.12.1.dist-info/RECORD
