Metadata-Version: 2.3
Name: apache-airflow-providers-ftp
Version: 3.12.1
Summary: Provider package apache-airflow-providers-ftp for Apache Airflow
Keywords: airflow-provider,ftp,airflow,integration
Author-email: Apache Software Foundation <dev@airflow.apache.org>
Maintainer-email: Apache Software Foundation <dev@airflow.apache.org>
Requires-Python: ~=3.9
Classifier: Development Status :: 5 - Production/Stable
Classifier: Environment :: Console
Classifier: Environment :: Web Environment
Classifier: Intended Audience :: Developers
Classifier: Intended Audience :: System Administrators
Classifier: Framework :: Apache Airflow
Classifier: Framework :: Apache Airflow :: Provider
Classifier: License :: OSI Approved :: Apache Software License
Classifier: Programming Language :: Python :: 3.9
Classifier: Programming Language :: Python :: 3.10
Classifier: Programming Language :: Python :: 3.11
Classifier: Programming Language :: Python :: 3.12
Classifier: Topic :: System :: Monitoring
Requires-Dist: apache-airflow>=2.9.0
Requires-Dist: apache-airflow-providers-common-compat ; extra == "common-compat"
Requires-Dist: apache-airflow-providers-openlineage ; extra == "openlineage"
Project-URL: Bug Tracker, https://github.com/apache/airflow/issues
Project-URL: Changelog, https://airflow.apache.org/docs/apache-airflow-providers-ftp/3.12.1/changelog.html
Project-URL: Documentation, https://airflow.apache.org/docs/apache-airflow-providers-ftp/3.12.1
Project-URL: Slack Chat, https://s.apache.org/airflow-slack
Project-URL: Source Code, https://github.com/apache/airflow
Project-URL: Twitter, https://x.com/ApacheAirflow
Project-URL: YouTube, https://www.youtube.com/channel/UCSXwxpWZQ7XZ1WL3wqevChA/
Provides-Extra: common-compat
Provides-Extra: openlineage
